{
  "chainId": 10,
  "reserves": {
    "0x76FB31fb4af56892A25e32cFC43De717950c9278": {
      "debtCeiling": 0,
      "variableDebtTokenImpl": "0x04a8D477eE202aDCE1682F5902e1160455205b12",
      "reserveFactor": 0,
      "liquidationThreshold": 6500,
      "isFlashloanable": true,
      "stableDebtTokenSymbol": "stableDebtOptAAVE",
      "stableDebtTokenName": "Aave Optimism Stable Debt AAVE",
      "oracleLatestAnswer": 6070485600,
      "aTokenName": "Aave Optimism AAVE",
      "usageAsCollateralEnabled": true,
      "aTokenSymbol": "aOptAAVE",
      "borrowCap": 0,
      "variableDebtTokenSymbol": "variableDebtOptAAVE",
      "supplyCap": 45000,
      "isFrozen": false,
      "stableDebtTokenImpl": "0x6b4E260b765B3cA1514e618C0215A6B7839fF93e",
      "oracleDescription": "AAVE / USD",
      "eModeCategory": 0,
      "liquidationProtocolFee": 1000,
      "isActive": true,
      "variableDebtTokenName": "Aave Optimism Variable Debt AAVE",
      "stableBorrowRateEnabled": false,
      "symbol": "AAVE",
      "isSiloed": false,
      "aTokenImpl": "0xbCb167bDCF14a8F791d6f4A6EDd964aed2F8813B",
      "variableDebtToken": "0xE80761Ea617F66F96274eA5e8c37f03960ecC679",
      "oracle": "0x338ed6787f463394D24813b297401B9F05a8C9d1",
      "isPaused": false,
      "liquidationBonus": 11000,
      "aToken": "0xf329e36C7bF6E5E86ce2150875a84Ce77f477375",
      "decimals": 18,
      "stableDebtToken": "0xfAeF6A702D15428E588d4C0614AEFb4348D83D48",
      "underlying": "0x76FB31fb4af56892A25e32cFC43De717950c9278",
      "borrowingEnabled": false,
      "oracleDecimals": 8,
      "interestRateStrategy": "0xeE1BAc9355EaAfCD1B68d272d640d870bC9b4b5C",
      "isBorrowableInIsolation": false,
      "ltv": 5000
    },
    "0x4200000000000000000000000000000000000042": {
      "isFrozen": false,
      "debtCeiling": 200000000,
      "stableDebtTokenName": "Aave Optimism Stable Debt OP",
      "isActive": true,
      "isBorrowableInIsolation": false,
      "stableDebtTokenImpl": "0x6b4E260b765B3cA1514e618C0215A6B7839fF93e",
      "usageAsCollateralEnabled": true,
      "liquidationProtocolFee": 1000,
      "variableDebtTokenImpl": "0x04a8D477eE202aDCE1682F5902e1160455205b12",
      "liquidationBonus": 11000,
      "aTokenName": "Aave Optimism OP",
      "borrowingEnabled": false,
      "supplyCap": 20000000,
      "reserveFactor": 2000,
      "underlying": "0x4200000000000000000000000000000000000042",
      "variableDebtTokenSymbol": "variableDebtOptOP",
      "aTokenImpl": "0xbCb167bDCF14a8F791d6f4A6EDd964aed2F8813B",
      "isPaused": false,
      "liquidationThreshold": 4000,
      "stableDebtToken": "0x08Cb71192985E936C7Cd166A8b268035e400c3c3",
      "borrowCap": 0,
      "aTokenSymbol": "aOptOP",
      "stableBorrowRateEnabled": false,
      "stableDebtTokenSymbol": "stableDebtOptOP",
      "ltv": 3000,
      "aToken": "0x513c7E3a9c69cA3e22550eF58AC1C0088e918FFf",
      "decimals": 18,
      "eModeCategory": 0,
      "oracleLatestAnswer": 152300000,
      "isFlashloanable": true,
      "variableDebtToken": "0x77CA01483f379E58174739308945f044e1a764dc",
      "isSiloed": false,
      "interestRateStrategy": "0xeE1BAc9355EaAfCD1B68d272d640d870bC9b4b5C",
      "variableDebtTokenName": "Aave Optimism Variable Debt OP",
      "oracle": "0x0D276FC14719f9292D5C1eA2198673d1f4269246",
      "oracleDescription": "OP / USD",
      "oracleDecimals": 8,
      "symbol": "OP"
    },
    "0x7F5c764cBc14f9669B88837ca1490cCa17c31607": {
      "decimals": 6,
      "isActive": true,
      "supplyCap": 150000000,
      "aTokenSymbol": "aOptUSDC",
      "eModeCategory": 1,
      "liquidationThreshold": 8500,
      "underlying": "0x7F5c764cBc14f9669B88837ca1490cCa17c31607",
      "stableDebtTokenSymbol": "stableDebtOptUSDC",
      "variableDebtTokenSymbol": "variableDebtOptUSDC",
      "oracle": "0x16a9FA2FDa030272Ce99B29CF780dFA30361E0f3",
      "oracleDescription": "USDC / USD",
      "oracleDecimals": 8,
      "isPaused": false,
      "oracleLatestAnswer": 100000000,
      "stableBorrowRateEnabled": true,
      "symbol": "USDC",
      "debtCeiling": 0,
      "usageAsCollateralEnabled": true,
      "variableDebtToken": "0xFCCf3cAbbe80101232d343252614b6A3eE81C989",
      "stableDebtTokenImpl": "0x6b4E260b765B3cA1514e618C0215A6B7839fF93e",
      "variableDebtTokenImpl": "0x04a8D477eE202aDCE1682F5902e1160455205b12",
      "liquidationBonus": 10500,
      "aTokenName": "Aave Optimism USDC",
      "variableDebtTokenName": "Aave Optimism Variable Debt USDC",
      "aToken": "0x625E7708f30cA75bfd92586e17077590C60eb4cD",
      "stableDebtTokenName": "Aave Optimism Stable Debt USDC",
      "liquidationProtocolFee": 1000,
      "aTokenImpl": "0xbCb167bDCF14a8F791d6f4A6EDd964aed2F8813B",
      "borrowCap": 100000000,
      "interestRateStrategy": "0x354E84ec43aCD91e1C0135c3e691960E881DB4b7",
      "isFrozen": false,
      "isFlashloanable": true,
      "stableDebtToken": "0x307ffe186F84a3bc2613D1eA417A5737D69A7007",
      "reserveFactor": 1000,
      "borrowingEnabled": true,
      "isBorrowableInIsolation": true,
      "ltv": 8000,
      "isSiloed": false
    },
    "0xc40F949F8a4e094D1b49a23ea9241D289B7b2819": {
      "stableDebtToken": "0x3EF10DFf4928279c004308EbADc4Db8B7620d6fc",
      "usageAsCollateralEnabled": false,
      "aToken": "0x8Eb270e296023E9D92081fdF967dDd7878724424",
      "liquidationThreshold": 0,
      "isPaused": false,
      "ltv": 0,
      "isBorrowableInIsolation": false,
      "oracle": "0x9dfc79Aaeb5bb0f96C6e9402671981CdFc424052",
      "stableDebtTokenImpl": "0x6b4E260b765B3cA1514e618C0215A6B7839fF93e",
      "oracleDescription": "LUSD / USD",
      "underlying": "0xc40F949F8a4e094D1b49a23ea9241D289B7b2819",
      "oracleLatestAnswer": 100566263,
      "aTokenName": "Aave Optimism LUSD",
      "symbol": "LUSD",
      "isSiloed": false,
      "variableDebtToken": "0xCE186F6Cccb0c955445bb9d10C59caE488Fea559",
      "isActive": true,
      "aTokenImpl": "0xbCb167bDCF14a8F791d6f4A6EDd964aed2F8813B",
      "interestRateStrategy": "0x271f5f8325051f22caDa18FfedD4a805584a232A",
      "variableDebtTokenImpl": "0x04a8D477eE202aDCE1682F5902e1160455205b12",
      "borrowCap": 1210000,
      "debtCeiling": 0,
      "decimals": 18,
      "variableDebtTokenSymbol": "variableDebtOptLUSD",
      "isFlashloanable": true,
      "stableDebtTokenName": "Aave Optimism Stable Debt LUSD",
      "liquidationBonus": 0,
      "isFrozen": false,
      "oracleDecimals": 8,
      "eModeCategory": 0,
      "supplyCap": 3000000,
      "variableDebtTokenName": "Aave Optimism Variable Debt LUSD",
      "stableBorrowRateEnabled": false,
      "borrowingEnabled": true,
      "liquidationProtocolFee": 0,
      "aTokenSymbol": "aOptLUSD",
      "stableDebtTokenSymbol": "stableDebtOptLUSD",
      "reserveFactor": 1000
    },
    "0x94b008aA00579c1307B0EF2c499aD98a8ce58e58": {
      "aTokenName": "Aave Optimism USDT",
      "reserveFactor": 1000,
      "decimals": 6,
      "debtCeiling": 500000000,
      "isActive": true,
      "isSiloed": false,
      "ltv": 7500,
      "underlying": "0x94b008aA00579c1307B0EF2c499aD98a8ce58e58",
      "liquidationThreshold": 8000,
      "variableDebtTokenImpl": "0x04a8D477eE202aDCE1682F5902e1160455205b12",
      "variableDebtTokenName": "Aave Optimism Variable Debt USDT",
      "liquidationBonus": 10500,
      "stableDebtToken": "0x70eFfc565DB6EEf7B927610155602d31b670e802",
      "stableDebtTokenImpl": "0x6b4E260b765B3cA1514e618C0215A6B7839fF93e",
      "oracleLatestAnswer": 100005485,
      "oracle": "0xECef79E109e997bCA29c1c0897ec9d7b03647F5E",
      "borrowCap": 16000000,
      "interestRateStrategy": "0xA9F3C3caE095527061e6d270DBE163693e6fda9D",
      "oracleDescription": "USDT / USD",
      "isPaused": false,
      "oracleDecimals": 8,
      "usageAsCollateralEnabled": true,
      "variableDebtToken": "0xfb00AC187a8Eb5AFAE4eACE434F493Eb62672df7",
      "variableDebtTokenSymbol": "variableDebtOptUSDT",
      "symbol": "USDT",
      "isBorrowableInIsolation": true,
      "aToken": "0x6ab707Aca953eDAeFBc4fD23bA73294241490620",
      "stableDebtTokenName": "Aave Optimism Stable Debt USDT",
      "stableBorrowRateEnabled": true,
      "isFrozen": false,
      "liquidationProtocolFee": 1000,
      "borrowingEnabled": true,
      "aTokenSymbol": "aOptUSDT",
      "eModeCategory": 1,
      "supplyCap": 25000000,
      "aTokenImpl": "0xbCb167bDCF14a8F791d6f4A6EDd964aed2F8813B",
      "stableDebtTokenSymbol": "stableDebtOptUSDT",
      "isFlashloanable": true
    },
    "0x4200000000000000000000000000000000000006": {
      "liquidationThreshold": 8250,
      "eModeCategory": 0,
      "aTokenSymbol": "aOptWETH",
      "variableDebtToken": "0x0c84331e39d6658Cd6e6b9ba04736cC4c4734351",
      "supplyCap": 35900,
      "isFrozen": false,
      "symbol": "WETH",
      "stableBorrowRateEnabled": false,
      "aTokenName": "Aave Optimism WETH",
      "usageAsCollateralEnabled": true,
      "interestRateStrategy": "0xc76EF342898f1AE7E6C4632627Df683FAD8563DD",
      "variableDebtTokenImpl": "0x04a8D477eE202aDCE1682F5902e1160455205b12",
      "aToken": "0xe50fA9b3c56FfB159cB0FCA61F5c9D750e8128c8",
      "stableDebtTokenImpl": "0x6b4E260b765B3cA1514e618C0215A6B7839fF93e",
      "oracle": "0x13e3Ee699D1909E989722E753853AE30b17e08c5",
      "underlying": "0x4200000000000000000000000000000000000006",
      "stableDebtTokenSymbol": "stableDebtOptWETH",
      "reserveFactor": 1500,
      "variableDebtTokenName": "Aave Optimism Variable Debt WETH",
      "borrowingEnabled": true,
      "oracleDescription": "ETH / USD",
      "debtCeiling": 0,
      "isPaused": false,
      "decimals": 18,
      "oracleDecimals": 8,
      "oracleLatestAnswer": 183288000000,
      "isFlashloanable": true,
      "aTokenImpl": "0xbCb167bDCF14a8F791d6f4A6EDd964aed2F8813B",
      "borrowCap": 19745,
      "liquidationProtocolFee": 1000,
      "ltv": 8000,
      "liquidationBonus": 10500,
      "isActive": true,
      "isBorrowableInIsolation": false,
      "stableDebtTokenName": "Aave Optimism Stable Debt WETH",
      "variableDebtTokenSymbol": "variableDebtOptWETH",
      "stableDebtToken": "0xD8Ad37849950903571df17049516a5CD4cbE55F6",
      "isSiloed": false
    },
    "0x1F32b1c2345538c0c6f582fCB022739c4A194Ebb": {
      "liquidationProtocolFee": 1000,
      "isFlashloanable": true,
      "variableDebtToken": "0x34e2eD44EF7466D5f9E0b782B5c08b57475e7907",
      "variableDebtTokenImpl": "0x04a8D477eE202aDCE1682F5902e1160455205b12",
      "liquidationBonus": 10720,
      "usageAsCollateralEnabled": true,
      "stableDebtToken": "0x78246294a4c6fBf614Ed73CcC9F8b875ca8eE841",
      "underlying": "0x1F32b1c2345538c0c6f582fCB022739c4A194Ebb",
      "symbol": "wstETH",
      "liquidationThreshold": 7900,
      "aToken": "0xc45A479877e1e9Dfe9FcD4056c699575a1045dAA",
      "aTokenSymbol": "aOptwstETH",
      "isPaused": false,
      "isSiloed": false,
      "oracleDecimals": 8,
      "oracleLatestAnswer": 206448505056,
      "isBorrowableInIsolation": false,
      "aTokenImpl": "0xbCb167bDCF14a8F791d6f4A6EDd964aed2F8813B",
      "isActive": true,
      "oracleName": "wstETH/ETH/USD",
      "ltv": 7000,
      "supplyCap": 18000,
      "borrowingEnabled": true,
      "interestRateStrategy": "0x6BA97468e2e6a3711a6DD05F0075d48E878c910e",
      "stableDebtTokenImpl": "0x6b4E260b765B3cA1514e618C0215A6B7839fF93e",
      "variableDebtTokenName": "Aave Optimism Variable Debt wstETH",
      "stableBorrowRateEnabled": false,
      "borrowCap": 940,
      "debtCeiling": 0,
      "isFrozen": false,
      "stableDebtTokenSymbol": "stableDebtOptwstETH",
      "aTokenName": "Aave Optimism wstETH",
      "eModeCategory": 0,
      "oracle": "0x05225Cd708bCa9253789C1374e4337a019e99D56",
      "stableDebtTokenName": "Aave Optimism Stable Debt wstETH",
      "decimals": 18,
      "variableDebtTokenSymbol": "variableDebtOptwstETH",
      "reserveFactor": 1500
    },
    "0x68f180fcCe6836688e9084f035309E29Bf0A2095": {
      "oracleLatestAnswer": 2590907568800,
      "variableDebtTokenSymbol": "variableDebtOptWBTC",
      "variableDebtTokenName": "Aave Optimism Variable Debt WBTC",
      "isActive": true,
      "aToken": "0x078f358208685046a11C85e8ad32895DED33A249",
      "isFlashloanable": true,
      "oracleDescription": "BTC / USD",
      "borrowingEnabled": true,
      "supplyCap": 1200,
      "aTokenSymbol": "aOptWBTC",
      "oracleDecimals": 8,
      "liquidationProtocolFee": 1000,
      "ltv": 7300,
      "decimals": 8,
      "isBorrowableInIsolation": false,
      "stableDebtToken": "0x633b207Dd676331c413D4C013a6294B0FE47cD0e",
      "symbol": "WBTC",
      "liquidationBonus": 10850,
      "usageAsCollateralEnabled": true,
      "stableBorrowRateEnabled": false,
      "stableDebtTokenName": "Aave Optimism Stable Debt WBTC",
      "stableDebtTokenImpl": "0x6b4E260b765B3cA1514e618C0215A6B7839fF93e",
      "oracle": "0xD702DD976Fb76Fffc2D3963D037dfDae5b04E593",
      "aTokenImpl": "0xbCb167bDCF14a8F791d6f4A6EDd964aed2F8813B",
      "underlying": "0x68f180fcCe6836688e9084f035309E29Bf0A2095",
      "isFrozen": false,
      "debtCeiling": 0,
      "variableDebtTokenImpl": "0x04a8D477eE202aDCE1682F5902e1160455205b12",
      "reserveFactor": 2000,
      "eModeCategory": 0,
      "interestRateStrategy": "0x04daBC3C1c052AB94AA2ca80140f2b978d2F6E17",
      "variableDebtToken": "0x92b42c66840C7AD907b4BF74879FF3eF7c529473",
      "liquidationThreshold": 7800,
      "borrowCap": 250,
      "aTokenName": "Aave Optimism WBTC",
      "isSiloed": false,
      "isPaused": false,
      "stableDebtTokenSymbol": "stableDebtOptWBTC"
    },
    "0xdFA46478F9e5EA86d57387849598dbFB2e964b02": {
      "variableDebtTokenSymbol": "variableDebtOptMAI",
      "underlying": "0xdFA46478F9e5EA86d57387849598dbFB2e964b02",
      "liquidationThreshold": 8000,
      "aToken": "0x8ffDf2DE812095b1D19CB146E4c004587C0A0692",
      "eModeCategory": 0,
      "isFrozen": false,
      "reserveFactor": 2000,
      "isFlashloanable": false,
      "aTokenImpl": "0xa5ba6E5EC19a1Bf23C857991c857dB62b2Aa187B",
      "stableDebtTokenSymbol": "stableDebtOptMAI",
      "variableDebtTokenName": "Aave Optimism Variable Debt MAI",
      "stableBorrowRateEnabled": false,
      "liquidationBonus": 10500,
      "liquidationProtocolFee": 1000,
      "oracleDecimals": 8,
      "oracleLatestAnswer": 99212145,
      "isPaused": true,
      "ltv": 7500,
      "isSiloed": false,
      "oracle": "0x73A3919a69eFCd5b19df8348c6740bB1446F5ed0",
      "decimals": 18,
      "oracleDescription": "MIMATIC / USD",
      "interestRateStrategy": "0xD624AFA34614B4fe7FEe7e1751a2E5E04fb47398",
      "borrowingEnabled": true,
      "usageAsCollateralEnabled": true,
      "aTokenSymbol": "aOptMAI",
      "variableDebtTokenImpl": "0x81387c40EB75acB02757C1Ae55D5936E78c9dEd3",
      "aTokenName": "Aave Optimism MAI",
      "stableDebtTokenName": "Aave Optimism Stable Debt MAI",
      "borrowCap": 2500000,
      "variableDebtToken": "0xA8669021776Bc142DfcA87c21b4A52595bCbB40a",
      "stableDebtToken": "0xa5e408678469d23efDB7694b1B0A85BB0669e8bd",
      "symbol": "MAI",
      "supplyCap": 7600000,
      "isActive": true,
      "isBorrowableInIsolation": false,
      "stableDebtTokenImpl": "0x52A1CeB68Ee6b7B5D13E0376A1E0E4423A8cE26e",
      "debtCeiling": 190000000
    },
    "0x350a791Bfc2C21F9Ed5d10980Dad2e2638ffa7f6": {
      "liquidationBonus": 11000,
      "aTokenSymbol": "aOptLINK",
      "borrowCap": 84000,
      "debtCeiling": 0,
      "borrowingEnabled": true,
      "aTokenImpl": "0xbCb167bDCF14a8F791d6f4A6EDd964aed2F8813B",
      "oracle": "0xCc232dcFAAE6354cE191Bd574108c1aD03f86450",
      "oracleDescription": "LINK / USD",
      "ltv": 7000,
      "isPaused": false,
      "symbol": "LINK",
      "interestRateStrategy": "0xeE1BAc9355EaAfCD1B68d272d640d870bC9b4b5C",
      "decimals": 18,
      "variableDebtTokenImpl": "0x04a8D477eE202aDCE1682F5902e1160455205b12",
      "oracleDecimals": 8,
      "supplyCap": 160000,
      "aToken": "0x191c10Aa4AF7C30e871E70C95dB0E4eb77237530",
      "reserveFactor": 2000,
      "aTokenName": "Aave Optimism LINK",
      "stableDebtTokenImpl": "0x6b4E260b765B3cA1514e618C0215A6B7839fF93e",
      "eModeCategory": 0,
      "liquidationProtocolFee": 1000,
      "isFrozen": false,
      "isFlashloanable": true,
      "stableDebtToken": "0x89D976629b7055ff1ca02b927BA3e020F22A44e4",
      "isActive": true,
      "stableDebtTokenName": "Aave Optimism Stable Debt LINK",
      "isSiloed": false,
      "variableDebtTokenSymbol": "variableDebtOptLINK",
      "isBorrowableInIsolation": false,
      "variableDebtTokenName": "Aave Optimism Variable Debt LINK",
      "variableDebtToken": "0x953A573793604aF8d41F306FEb8274190dB4aE0e",
      "oracleLatestAnswer": 618600000,
      "usageAsCollateralEnabled": true,
      "stableDebtTokenSymbol": "stableDebtOptLINK",
      "liquidationThreshold": 7500,
      "underlying": "0x350a791Bfc2C21F9Ed5d10980Dad2e2638ffa7f6",
      "stableBorrowRateEnabled": false
    },
    "0xDA10009cBd5D07dd0CeCc66161FC93D7c9000da1": {
      "decimals": 18,
      "liquidationBonus": 10500,
      "isFlashloanable": true,
      "borrowCap": 16000000,
      "aTokenImpl": "0xbCb167bDCF14a8F791d6f4A6EDd964aed2F8813B",
      "stableDebtTokenSymbol": "stableDebtOptDAI",
      "variableDebtToken": "0x8619d80FB0141ba7F184CbF22fd724116D9f7ffC",
      "variableDebtTokenImpl": "0x04a8D477eE202aDCE1682F5902e1160455205b12",
      "aToken": "0x82E64f49Ed5EC1bC6e43DAD4FC8Af9bb3A2312EE",
      "aTokenName": "Aave Optimism DAI",
      "variableDebtTokenSymbol": "variableDebtOptDAI",
      "interestRateStrategy": "0xA9F3C3caE095527061e6d270DBE163693e6fda9D",
      "borrowingEnabled": true,
      "variableDebtTokenName": "Aave Optimism Variable Debt DAI",
      "ltv": 7800,
      "oracleDescription": "DAI / USD",
      "stableDebtTokenImpl": "0x6b4E260b765B3cA1514e618C0215A6B7839fF93e",
      "underlying": "0xDA10009cBd5D07dd0CeCc66161FC93D7c9000da1",
      "oracleLatestAnswer": 99997166,
      "oracleDecimals": 8,
      "isActive": true,
      "isFrozen": false,
      "aTokenSymbol": "aOptDAI",
      "isSiloed": false,
      "stableDebtTokenName": "Aave Optimism Stable Debt DAI",
      "stableDebtToken": "0xd94112B5B62d53C9402e7A60289c6810dEF1dC9B",
      "reserveFactor": 1000,
      "isBorrowableInIsolation": true,
      "usageAsCollateralEnabled": true,
      "symbol": "DAI",
      "eModeCategory": 1,
      "liquidationThreshold": 8300,
      "isPaused": false,
      "stableBorrowRateEnabled": true,
      "liquidationProtocolFee": 1000,
      "supplyCap": 25000000,
      "oracle": "0x8dBa75e83DA73cc766A7e5a0ee71F656BAb470d6",
      "debtCeiling": 0
    },
    "0x8c6f28f2F1A3C87F0f938b96d27520d9751ec8d9": {
      "variableDebtTokenImpl": "0x04a8D477eE202aDCE1682F5902e1160455205b12",
      "liquidationBonus": 10540,
      "symbol": "sUSD",
      "aTokenName": "Aave Optimism SUSD",
      "variableDebtTokenName": "Aave Optimism Variable Debt SUSD",
      "isSiloed": false,
      "interestRateStrategy": "0xA9F3C3caE095527061e6d270DBE163693e6fda9D",
      "liquidationProtocolFee": 1000,
      "isActive": true,
      "aTokenImpl": "0xbCb167bDCF14a8F791d6f4A6EDd964aed2F8813B",
      "oracleLatestAnswer": 99786524,
      "oracleDecimals": 8,
      "aTokenSymbol": "aOptSUSD",
      "reserveFactor": 1000,
      "debtCeiling": 0,
      "ltv": 6000,
      "usageAsCollateralEnabled": true,
      "stableDebtTokenImpl": "0x6b4E260b765B3cA1514e618C0215A6B7839fF93e",
      "stableDebtToken": "0xF15F26710c827DDe8ACBA678682F3Ce24f2Fb56E",
      "decimals": 18,
      "stableDebtTokenSymbol": "stableDebtOptSUSD",
      "underlying": "0x8c6f28f2F1A3C87F0f938b96d27520d9751ec8d9",
      "isFlashloanable": true,
      "oracleDescription": "SUSD / USD",
      "supplyCap": 20000000,
      "stableBorrowRateEnabled": false,
      "aToken": "0x6d80113e533a2C0fe82EaBD35f1875DcEA89Ea97",
      "oracle": "0x7f99817d87baD03ea21E05112Ca799d715730efe",
      "stableDebtTokenName": "Aave Optimism Stable Debt SUSD",
      "isPaused": false,
      "variableDebtToken": "0x4a1c3aD6Ed28a636ee1751C69071f6be75DEb8B8",
      "variableDebtTokenSymbol": "variableDebtOptSUSD",
      "liquidationThreshold": 7500,
      "borrowCap": 13000000,
      "eModeCategory": 1,
      "borrowingEnabled": true,
      "isBorrowableInIsolation": false,
      "isFrozen": false
    }
  }
}